CHANGES.rst
LICENSE
MANIFEST.in
NOTICE
README.rst
setup.py
doc/Makefile
doc/conf.py
doc/index.rst
doc/installation.rst
doc/introduction.rst
doc/make.bat
doc/plugins.rst
doc/theme/bs/layout.html
doc/theme/bs/theme.conf
doc/theme/bs/static/bs.css
doc/theme/bs/static/jquery.js
doc/theme/bs/static/restyle.js
doc/theme/bs/static/bootstrap/css/bootstrap-responsive.css
doc/theme/bs/static/bootstrap/css/bootstrap-responsive.min.css
doc/theme/bs/static/bootstrap/css/bootstrap.css
doc/theme/bs/static/bootstrap/css/bootstrap.min.css
doc/theme/bs/static/bootstrap/img/glyphicons-halflings-white.png
doc/theme/bs/static/bootstrap/img/glyphicons-halflings.png
doc/theme/bs/static/bootstrap/js/bootstrap.js
doc/theme/bs/static/bootstrap/js/bootstrap.min.js
src/ralph_pricing/__init__.py
src/ralph_pricing/admin.py
src/ralph_pricing/api.py
src/ralph_pricing/app.py
src/ralph_pricing/forms.py
src/ralph_pricing/menus.py
src/ralph_pricing/models.py
src/ralph_pricing/openstack.py
src/ralph_pricing/splunk.py
src/ralph_pricing/urls.py
src/ralph_pricing/utils.py
src/ralph_pricing/fixtures/tests.yaml
src/ralph_pricing/management/__init__.py
src/ralph_pricing/management/commands/__init__.py
src/ralph_pricing/management/commands/pricing_fix_blades.py
src/ralph_pricing/management/commands/pricing_statistics.py
src/ralph_pricing/management/commands/pricing_sync.py
src/ralph_pricing/media/scrooge/css/style.css
src/ralph_pricing/media/scrooge/js/table_fixed_header.js
src/ralph_pricing/migrations/0001_initial.py
src/ralph_pricing/migrations/0002_auto__add_field_venture_symbol.py
src/ralph_pricing/migrations/0003_auto__add_field_usagetype_average__add_field_usagetype_show_value_perc.py
src/ralph_pricing/migrations/0004_auto__add_field_dailydevice_deprecation_rate__add_field_dailypart_depr.py
src/ralph_pricing/migrations/0005_auto__add_splunkname__add_unique_splunkname_splunk_name_pricing_device.py
src/ralph_pricing/migrations/0006_auto__add_field_venture_business_segment__add_field_venture_pricing_ce.py
src/scrooge.egg-info/PKG-INFO
src/scrooge.egg-info/SOURCES.txt
src/scrooge.egg-info/dependency_links.txt
src/scrooge.egg-info/entry_points.txt
src/scrooge.egg-info/not-zip-safe
src/scrooge.egg-info/requires.txt
src/scrooge.egg-info/top_level.txt